dau_active_inference/__init__.py
dau_active_inference/dau_active_inference.py
dau_active_inference-1.0.3.dist-info/LICENSE
dau_active_inference-1.0.3.dist-info/METADATA
dau_active_inference-1.0.3.dist-info/WHEEL
dau_active_inference-1.0.3.dist-info/entry_points.txt
dau_active_inference-1.0.3.dist-info/top_level.txt
dau_active_inference-1.0.3.dist-info/RECORD
