Metadata-Version: 2.2
Name: dau-active-inference
Version: 1.0.3
Summary: Multi-agent active inference with PyMDP
Home-page: https://github.com/LearnableLoopAI/Designer-Artifact-User
Author: LearnableLoopAI.com / UltimIT.us
Author-email: kobus.esterhuysen.ai@gmail.com
Classifier: Programming Language :: Python :: 3
Classifier: License :: OSI Approved :: MIT License
Classifier: Operating System :: Unix
Requires-Python: >=3.12
License-File: LICENSE
Requires-Dist: pymdp
Requires-Dist: numpy
Requires-Dist: matplotlib
Requires-Dist: inferactively-pymdp
Dynamic: author
Dynamic: author-email
Dynamic: classifier
Dynamic: description
Dynamic: description-content-type
Dynamic: home-page
Dynamic: requires-dist
Dynamic: requires-python
Dynamic: summary
